{
  "gameBoard": [
    [
      {
        "unit": {
          "name": "Hunter",
          "quantity": 3
        }
      },
      {
        "unit": {
          "name": "",
          "quantity": 0
        }
      },
      {
        "unit": {
          "name": "Electro Robot",
          "quantity": 1
        }
      },
      {
        "unit": {
          "name": "",
          "quantity": 0
        }
      },
      {
        "unit": {
          "name": "",
          "quantity": 0
        }
      },
      {
        "unit": {
          "name": "",
          "quantity": 0
        }
      }
    ],
    [
      {
        "unit": {
          "name": "Bandit",
          "quantity": 3
        }
      },
      {
        "unit": {
          "name": "Archer",
          "quantity": 1
        }
      },
      {
        "unit": {
          "name": "Eagle General",
          "quantity": 3
        }
      },
      {
        "unit": {
          "name": "Tree",
          "quantity": 3
        }
      },
      {
        "unit": {
          "name": "",
          "quantity": 0
        }
      },
      {
        "unit": {
          "name": "",
          "quantity": 0
        }
      }
    ],
    [
      {
        "unit": {
          "name": "",
          "quantity": 0
        }
      },
      {
        "unit": {
          "name": "Wolf Warrior",
          "quantity": 1
        }
      },
      {
        "unit": {
          "name": "Water Elemental",
          "quantity": 2
        }
      },
      {
        "unit": {
          "name": "",
          "quantity": 0
        }
      },
      {
        "unit": {
          "name": "",
          "quantity": 0
        }
      },
      {
        "unit": {
          "name": "",
          "quantity": 0
        }
      }
    ]
  ]
}